classroom_gizmos/BestByMinBefore.py
classroom_gizmos/__init__.py
classroom_gizmos/fdtest.py
classroom_gizmos/handies.py
classroom_gizmos/import_install.py
classroom_gizmos/jupyter_file_browser.py
classroom_gizmos/main.py
classroom_gizmos/timestamp.txt
classroom_gizmos-0.0b2.dev32.dist-info/LICENSE
classroom_gizmos-0.0b2.dev32.dist-info/METADATA
classroom_gizmos-0.0b2.dev32.dist-info/WHEEL
classroom_gizmos-0.0b2.dev32.dist-info/top_level.txt
classroom_gizmos-0.0b2.dev32.dist-info/RECORD
