Metadata-Version: 2.1
Name: classroom-gizmos
Version: 0.0b2.dev32
Summary: Several small functions for classroom instruction.
Home-page: https://github.com/Danseur1/Classroom_gizmos
Author: Carl Schmiedekamp
Author-email: cw2@psu.edu
License: UNKNOWN
Platform: UNKNOWN
Classifier: Programming Language :: Python :: 3
Classifier: License :: OSI Approved :: GNU General Public License v3 or later (GPLv3+)
Classifier: Operating System :: OS Independent
Classifier: Development Status :: 3 - Alpha
Requires-Python: >=3.6
